{
  "coc.preferences.extensionUpdateCheck": "daily",
  "coc.preferences.enableMessageDialog": true,
  "coc.preferences.formatOnType": true,
  "coc.preferences.willSaveHandlerTimeout": 1000,
  "coc.preferences.enableLinkedEditing": true,
  "diagnostic.virtualTextCurrentLineOnly": false,
  "coc.preferences.formatOnSaveFiletypes": [
    "css",
    "markdown",
    "tsx",
    "css",
    "javascript",
    "javascriptreact",
    "typescript",
    "typescriptreact",
    "json"
  ],
  "suggest.minTriggerInputLength": 2,
  "snippets.autoTrigger": true,
  "eslint.run": "onSave",
  "eslint.autoFixOnSave": true,
  "eslint.format.enable": true,
  "eslint.packageManager": "yarn",
  "typescript.suggest.autoImports": true,
  "diagnostic.floatConfig": {
    "rounded": true,
    "border": true
  },
  "diagnostic.format": "%message [%source]",
  "diagnostic.virtualText": false,
  "diagnostic.errorSign": "",
  "diagnostic.warningSign": "",
  "diagnostic.infoSign": "",
  "diagnostic.enableMessage": "jump",
  "diagnostic.checkCurrentLine": true,
  "diagnostic.separateRelatedInformationAsDiagnostics": true,
  "git.addGBlameToVirtualText": false,
  "suggest.completionItemKindLabels": {
    "method": "  ",
    "function": "  ",
    "variable": "[]",
    "field": "  ",
    "typeParameter": "<>",
    "constant": "  ",
    "class": " פּ ",
    "interface": " 蘒",
    "struct": "  ",
    "event": "  ",
    "operator": "  ",
    "module": "  ",
    "property": "  ",
    "enum": " 練",
    "reference": "  ",
    "keyword": "  ",
    "file": "  ",
    "folder": " ﱮ ",
    "color": "  ",
    "unit": " 塞 ",
    "snippet": "  ",
    "text": "  ",
    "constructor": "  ",
    "value": "  ",
    "enumMember": "  "
  }
}
